grilled/common/__init__.py
grilled/common/data_structure/external.py
grilled/common/data_structure/internal.py
grilled/common/logger.py
grilled/common/loop.py
grilled/common/note.py
grilled_common-0.2.5.dist-info/WHEEL
grilled_common-0.2.5.dist-info/METADATA
grilled_common-0.2.5.dist-info/RECORD
