Metadata-Version: 2.1
Name: grilled-common
Version: 0.2.5
Summary: 
Author: hans
Author-email: dxzenghan@163.com
Requires-Python: >=3.7,<4.0
Classifier: Programming Language :: Python :: 3
Classifier: Programming Language :: Python :: 3.7
Classifier: Programming Language :: Python :: 3.8
Classifier: Programming Language :: Python :: 3.9
Requires-Dist: logging
Requires-Dist: pydantic (<=1.7.1)
